{
  "routes": [
    {
      "method": "GET",
      "path": "/intros",
      "handler": "Intro.find",
      "config": {
        "policies": []
      }
    },
    {
      "method": "GET",
      "path": "/intros/count",
      "handler": "Intro.count",
      "config": {
        "policies": []
      }
    },
    {
      "method": "GET",
      "path": "/intros/:id",
      "handler": "Intro.findOne",
      "config": {
        "policies": []
      }
    },
    {
      "method": "POST",
      "path": "/intros",
      "handler": "Intro.create",
      "config": {
        "policies": []
      }
    },
    {
      "method": "PUT",
      "path": "/intros/:id",
      "handler": "Intro.update",
      "config": {
        "policies": []
      }
    },
    {
      "method": "DELETE",
      "path": "/intros/:id",
      "handler": "Intro.delete",
      "config": {
        "policies": []
      }
    }
  ]
}
